libfaketimefs_ctl/__init__.py
libfaketimefs_ctl-0.0.8.data/scripts/libfaketimefs-ctl
libfaketimefs_ctl-0.0.8.dist-info/METADATA
libfaketimefs_ctl-0.0.8.dist-info/RECORD
libfaketimefs_ctl-0.0.8.dist-info/WHEEL
libfaketimefs_ctl-0.0.8.dist-info/top_level.txt
