Metadata-Version: 2.1
Name: libfaketimefs-ctl
Version: 0.0.8
Summary: libfaketimefs controller
Home-page: https://github.com/claranet/libfaketimefs-ctl
Author: Raymond Butcher
Author-email: ray.butcher@claranet.uk
License: MIT License
Platform: UNKNOWN
Requires-Dist: boto3
Requires-Dist: libfaketimefs-botocore (>=0.0.2)
Requires-Dist: py-dateutil
